interage/__init__.py
interage/api/__init__.py
interage/api/base.py
interage/api/client.py
interage/api/config/__init__.py
interage/api/config/consts.py
interage/api/config/settings.py
interage/api/exceptions/__init__.py
interage/api/exceptions/attribute.py
interage/api/exceptions/http.py
interage/api/exceptions/messages.py
interage/api/managers/__init__.py
interage/api/managers/base.py
interage/api/managers/managers.py
interage/api/managers/mixins.py
interage/api/models/__init__.py
interage/api/models/base.py
interage/api/models/metadata.py
interage/api/models/mixins.py
interage/api/models/models.py
interage/api/models/properties.py
interage/api/models/result.py
interage/api/utils/__init__.py
interage/api/utils/models.py
interage/api/utils/strings.py
interage_python_sdk-0.4.0.dist-info/DESCRIPTION.rst
interage_python_sdk-0.4.0.dist-info/METADATA
interage_python_sdk-0.4.0.dist-info/RECORD
interage_python_sdk-0.4.0.dist-info/WHEEL
interage_python_sdk-0.4.0.dist-info/metadata.json
interage_python_sdk-0.4.0.dist-info/top_level.txt
