Metadata-Version: 2.0
Name: interage-python-sdk
Version: 0.4.0
Summary: SDK oficialmente mantido pela IntMed Software para auxiliar no desenvolvimento de aplicações em Python integradas ao serviço de interações medicamentosas do sistema Interage
Home-page: https://github.com/IntMed/interage_python_sdk
Author: IntMed Software
Author-email: contato@intmed.com.br
License: UNKNOWN
Download-URL: https://github.com/IntMed/interage_python_sdk/archive/0.4.0.tar.gz
Keywords: interage intmed api python sdk
Platform: UNKNOWN
